pretix_vacc_autosched/__init__.py
pretix_vacc_autosched/api.py
pretix_vacc_autosched/forms.py
pretix_vacc_autosched/models.py
pretix_vacc_autosched/signals.py
pretix_vacc_autosched/tasks.py
pretix_vacc_autosched/urls.py
pretix_vacc_autosched/views.py
pretix_vacc_autosched/migrations/0001_initial.py
pretix_vacc_autosched/migrations/0002_auto_20210310_1210.py
pretix_vacc_autosched/migrations/0003_itemconfig_max_days.py
pretix_vacc_autosched/migrations/0004_itemconfig_second_item.py
pretix_vacc_autosched/migrations/__init__.py
pretix_vacc_autosched/static/pretix_vacc_autosched/style.css
pretix_vacc_autosched/templates/pretix_vacc_autosched/self_service_index.html
pretix_vacc_autosched/templates/pretix_vacc_autosched/self_service_order.html
pretix_vacc_autosched/templates/pretix_vacc_autosched/settings.html
pretix_vacc_autosched/templates/pretix_vacc_autosched/thanks.html
pretix_vacc_utils-2.5.1.dist-info/LICENSE
pretix_vacc_utils-2.5.1.dist-info/METADATA
pretix_vacc_utils-2.5.1.dist-info/WHEEL
pretix_vacc_utils-2.5.1.dist-info/entry_points.txt
pretix_vacc_utils-2.5.1.dist-info/top_level.txt
pretix_vacc_utils-2.5.1.dist-info/RECORD
