Metadata-Version: 2.1
Name: pretix-vacc-utils
Version: 2.5.1
Summary: Various vaccination utilities
Home-page: https://github.com/pretix-unofficial/pretix-vacc-utils
Author: pretix team
Author-email: support@pretix.eu
License: Apache
Platform: UNKNOWN
